Metadata-Version: 2.1
Name: ammarpy
Version: 0.0
Summary: Just for fun, doesn't contains any useful function
Author-email: sjahnaviprasad@gmail.com
